odoo/addons/fieldservice_vehicle_stock_request/README.rst
odoo/addons/fieldservice_vehicle_stock_request/__init__.py
odoo/addons/fieldservice_vehicle_stock_request/__manifest__.py
odoo/addons/fieldservice_vehicle_stock_request/i18n/es.po
odoo/addons/fieldservice_vehicle_stock_request/i18n/es_AR.po
odoo/addons/fieldservice_vehicle_stock_request/i18n/fieldservice_vehicle_stock_request.pot
odoo/addons/fieldservice_vehicle_stock_request/i18n/it.po
odoo/addons/fieldservice_vehicle_stock_request/i18n/pt_BR.po
odoo/addons/fieldservice_vehicle_stock_request/models/__init__.py
odoo/addons/fieldservice_vehicle_stock_request/models/stock_request.py
odoo/addons/fieldservice_vehicle_stock_request/readme/CONTRIBUTORS.rst
odoo/addons/fieldservice_vehicle_stock_request/readme/CREDITS.rst
odoo/addons/fieldservice_vehicle_stock_request/readme/DESCRIPTION.rst
odoo/addons/fieldservice_vehicle_stock_request/readme/ROADMAP.rst
odoo/addons/fieldservice_vehicle_stock_request/static/description/icon.png
odoo/addons/fieldservice_vehicle_stock_request/static/description/index.html
odoo/addons/fieldservice_vehicle_stock_request/tests/__init__.py
odoo/addons/fieldservice_vehicle_stock_request/tests/test_fsm_vehicle_stock_request.py
odoo/addons/fieldservice_vehicle_stock_request/views/fsm_order.xml
odoo14_addon_fieldservice_vehicle_stock_request-14.0.1.0.1.dev12.dist-info/METADATA
odoo14_addon_fieldservice_vehicle_stock_request-14.0.1.0.1.dev12.dist-info/WHEEL
odoo14_addon_fieldservice_vehicle_stock_request-14.0.1.0.1.dev12.dist-info/top_level.txt
odoo14_addon_fieldservice_vehicle_stock_request-14.0.1.0.1.dev12.dist-info/RECORD
